billing_sync/__init__.py
billing_sync/APIs/__init__.py
billing_sync/APIs/api_format.py
billing_sync/APIs/utils/__init__.py
billing_sync/APIs/utils/generate_code.py
billing_sync/Nash/__init__.py
billing_sync/Nash/nash.py
billing_sync/Resources/__init__.py
billing_sync/Resources/billers.py
billing_sync/Resources/billing.py
billing_sync/Resources/operations.py
billing_sync/Resources/resource.py
nashbillingsync-0.0.10.dist-info/LICENSE
nashbillingsync-0.0.10.dist-info/METADATA
nashbillingsync-0.0.10.dist-info/WHEEL
nashbillingsync-0.0.10.dist-info/top_level.txt
nashbillingsync-0.0.10.dist-info/RECORD
