Metadata-Version: 2.1
Name: nashbillingsync
Version: 0.0.10
Summary: Python library for connecting to the Nash Billing Framework
Home-page: https://nashbillingsync.readme.io/docs
Author: Dansol Obondo
Author-email: dansol@nashafrica.co
License: UNKNOWN
Platform: UNKNOWN
Classifier: Programming Language :: Python :: 3
Classifier: Programming Language :: Python :: 3.6
Classifier: Programming Language :: Python :: 3.7
Classifier: License :: OSI Approved :: MIT License
Classifier: Operating System :: OS Independent
License-File: LICENSE
